{"title":"Basic Marks: line","subtitle":"Tutorial Examples","tracks":[{"title":"Basic Marks: line","subtitle":"Tutorial Examples","assembly":"hg38","layout":"linear","orientation":"horizontal","static":false,"zoomLimits":[1,null],"centerRadius":0.3,"spacing":10,"xOffset":0,"yOffset":0,"width":392,"height":156,"data":{"url":"https://resgen.io/api/v1/tileset_info/?d=UvVPeLHuRDiYA3qwFlm7xQ","type":"multivec","row":"sample","column":"position","value":"peak","categories":["sample 1"]},"mark":"line","x":{"field":"position","type":"genomic","axis":"bottom","linkingId":"8d7329b9-bbc1-4467-a14d-ac896c2ef50e"},"y":{"field":"peak","type":"quantitative","axis":"right"},"size":{"value":2},"color":{"value":"#fc8585"},"id":"e2d343cd-536a-451f-894e-96006dfa7a86","style":{},"overlayOnPreviousTrack":false}],"assembly":"hg38","layout":"linear","orientation":"horizontal","static":false,"zoomLimits":[1,null],"centerRadius":0.3,"spacing":10,"xOffset":0,"yOffset":0,"id":"73cd7b52-60e5-45f3-90a7-699be3c240e1","_assignedWidth":392,"_assignedHeight":156}