{"xDomain":{"interval":[800000000,1800000000]},"views":[{"tracks":[{"width":630,"height":630,"assembly":"hg38","layout":"linear","orientation":"horizontal","static":false,"zoomLimits":[1,null],"xDomain":{"interval":[800000000,1800000000]},"centerRadius":0.3,"xOffset":0,"yOffset":0,"style":{},"data":{"url":"https://server.gosling-lang.org/api/v1/tileset_info/?d=leung2015-hg38","type":"matrix"},"mark":"rect","x":{"field":"xs","type":"genomic","axis":"top","domain":{"interval":[800000000,1800000000]},"linkingId":"5a9c8085-1ede-4ebe-bd50-da4100dd6ad4"},"xe":{"field":"xe","type":"genomic","axis":"none"},"y":{"field":"ys","type":"genomic","axis":"left"},"ye":{"field":"ye","type":"genomic"},"color":{"field":"value","type":"quantitative","range":"hot"},"id":"e9fdf906-95ae-4d7e-a182-dca2817c3823","overlayOnPreviousTrack":false}],"width":600,"height":600,"assembly":"hg38","layout":"linear","orientation":"horizontal","static":false,"zoomLimits":[1,null],"xDomain":{"interval":[800000000,1800000000]},"centerRadius":0.3,"xOffset":0,"yOffset":0,"style":{},"id":"9f32c6ca-479b-44e9-9d16-8f70c2e27e8c","_assignedWidth":630,"_assignedHeight":630}],"assembly":"hg38","layout":"linear","orientation":"horizontal","static":false,"zoomLimits":[1,null],"centerRadius":0.3,"spacing":10,"arrangement":"vertical","xOffset":0,"yOffset":0,"id":"9a7cb026-b5da-45cb-a2e1-68334b8cc9cc","_assignedWidth":630,"_assignedHeight":630}