{"title":"Example: Overlayed Tracks","tracks":[{"height":170,"width":840,"layout":"linear","data":{"url":"https://resgen.io/api/v1/tileset_info/?d=UvVPeLHuRDiYA3qwFlm7xQ","type":"multivec","row":"sample","column":"position","value":"peak","categories":["sample 1","sample 2","sample 3","sample 4"]},"x":{"field":"position","type":"genomic","domain":{"chromosome":"chr1","interval":[1,3000500]},"axis":"top","linkingId":"2a5c3731-0aad-4440-a3af-28b2fd458198"},"y":{"field":"peak","type":"quantitative"},"row":{"field":"sample","type":"nominal"},"color":{"field":"sample","type":"nominal","range":["#1f77b4","#ff7f0e","#2ca02c","#d62728","#9467bd","#8c564b","#e377c2","#7f7f7f","#bcbd22","#17becf"]},"_overlay":[{"mark":"line","style":{}},{"mark":"point","size":{"field":"peak","type":"quantitative","range":[0,6]},"style":{}}],"id":"810476e2-0f88-4bd7-bd5d-93a6ae20ae26","assembly":"hg38","orientation":"horizontal","static":false,"zoomLimits":[1,null],"style":{},"overlayOnPreviousTrack":false}],"assembly":"hg38","layout":"linear","orientation":"horizontal","static":false,"zoomLimits":[1,null],"centerRadius":0.3,"spacing":10,"xOffset":0,"yOffset":0,"id":"3557476f-5578-459c-8aaf-9b5897cd019d","_assignedWidth":840,"_assignedHeight":170}