{"layout":"linear","arrangement":"vertical","centerRadius":0.8,"xDomain":{"chromosome":"chr1","interval":[1,3000500]},"views":[{"tracks":[{"assembly":"hg38","layout":"linear","orientation":"horizontal","static":false,"zoomLimits":[1,null],"xDomain":{"chromosome":"chr1","interval":[1,3000500]},"centerRadius":0.8,"xOffset":0,"yOffset":0,"style":{},"id":"track-1","data":{"url":"https://server.gosling-lang.org/api/v1/tileset_info/?d=cistrome-multivec","type":"multivec","row":"sample","column":"position","value":"peak","categories":["sample 1","sample 2","sample 3","sample 4"],"binSize":4},"mark":"rect","x":{"field":"start","type":"genomic","axis":"top","domain":{"chromosome":"chr1","interval":[1,3000500]},"linkingId":"e483c8dd-5c8d-4e76-afd7-f81cd7153594"},"xe":{"field":"end","type":"genomic"},"row":{"field":"sample","type":"nominal","legend":true},"color":{"field":"peak","type":"quantitative","legend":true},"tooltip":[{"field":"start","type":"genomic","alt":"Start Position"},{"field":"end","type":"genomic","alt":"End Position"},{"field":"peak","type":"quantitative","alt":"Value","format":".2"},{"field":"sample","type":"nominal","alt":"Sample"}],"width":600,"height":160,"overlayOnPreviousTrack":false}],"assembly":"hg38","layout":"linear","orientation":"horizontal","static":false,"zoomLimits":[1,null],"xDomain":{"chromosome":"chr1","interval":[1,3000500]},"centerRadius":0.8,"xOffset":0,"yOffset":0,"style":{},"id":"c3d5cf54-5992-45ad-8391-84f08fe4b855","_assignedWidth":600,"_assignedHeight":160},{"tracks":[{"assembly":"hg38","layout":"linear","orientation":"horizontal","static":false,"zoomLimits":[1,null],"xDomain":{"chromosome":"chr1","interval":[1,3000500]},"centerRadius":0.8,"xOffset":0,"yOffset":0,"style":{},"id":"track-2","data":{"url":"https://server.gosling-lang.org/api/v1/tileset_info/?d=cistrome-multivec","type":"multivec","row":"sample","column":"position","value":"peak","categories":["sample 1","sample 2","sample 3","sample 4"]},"mark":"bar","x":{"field":"position","type":"genomic","axis":"top","domain":{"chromosome":"chr1","interval":[1,3000500]},"linkingId":"f4e840f8-a268-425f-9e23-3813bca12430"},"y":{"field":"peak","type":"quantitative"},"row":{"field":"sample","type":"nominal"},"color":{"field":"sample","type":"nominal","legend":true},"tooltip":[{"field":"start","type":"genomic","alt":"Start Position"},{"field":"end","type":"genomic","alt":"End Position"},{"field":"peak","type":"quantitative","alt":"Value","format":".2"},{"field":"sample","type":"nominal","alt":"Sample"}],"width":600,"height":160,"overlayOnPreviousTrack":false}],"assembly":"hg38","layout":"linear","orientation":"horizontal","static":false,"zoomLimits":[1,null],"xDomain":{"chromosome":"chr1","interval":[1,3000500]},"centerRadius":0.8,"xOffset":0,"yOffset":0,"style":{},"id":"2aaddc13-7a4c-4abd-b275-212853973bc7","_assignedWidth":600,"_assignedHeight":160}],"assembly":"hg38","orientation":"horizontal","static":false,"zoomLimits":[1,null],"spacing":10,"xOffset":0,"yOffset":0,"id":"2d0112c5-b0a6-45bf-85e9-baf5db223d86","_assignedWidth":600,"_assignedHeight":330}